{
  "experiment": "catboost_tweedie_vp1.5",
  "horizon": 1,
  "target_col": "points_next_gw",
  "holdout_season": "2024-25",
  "train_seasons": [
    "2016-17",
    "2017-18",
    "2018-19",
    "2019-20",
    "2020-21",
    "2021-22",
    "2022-23",
    "2023-24"
  ],
  "n_train": 185149,
  "n_test": 26000,
  "n_features": 116,
  "variance_power": 1.5,
  "top_features": [
    {
      "feature": "value",
      "importance": 11.852920587728862
    },
    {
      "feature": "GW",
      "importance": 9.429905627004786
    },
    {
      "feature": "minutes_season_avg",
      "importance": 6.292910509822964
    },
    {
      "feature": "position",
      "importance": 4.723217799044704
    },
    {
      "feature": "bps_season_avg",
      "importance": 4.5936000570596605
    },
    {
      "feature": "total_points_season_avg",
      "importance": 4.339609778709801
    },
    {
      "feature": "influence_season_avg",
      "importance": 4.214541492514362
    },
    {
      "feature": "games_since_start",
      "importance": 4.061164720271492
    },
    {
      "feature": "minutes_roll10",
      "importance": 3.504843180409002
    },
    {
      "feature": "minutes_roll5",
      "importance": 2.9718713911588277
    },
    {
      "feature": "minutes_lag1",
      "importance": 2.711901271082069
    },
    {
      "feature": "minutes_trend",
      "importance": 2.5839769475503434
    },
    {
      "feature": "us_xg_roll10",
      "importance": 1.9509848832165857
    },
    {
      "feature": "ict_index_roll10",
      "importance": 1.902003862691903
    },
    {
      "feature": "creativity_roll10",
      "importance": 1.8501096289118046
    },
    {
      "feature": "creativity_roll5",
      "importance": 1.8434673248913718
    },
    {
      "feature": "us_xgbuildup_roll10",
      "importance": 1.7580893302485483
    },
    {
      "feature": "played_lag1",
      "importance": 1.7362886346973914
    },
    {
      "feature": "influence_roll10",
      "importance": 1.3485722618113138
    },
    {
      "feature": "total_points_roll10",
      "importance": 1.3474585302212176
    }
  ],
  "holdout": {
    "model": {
      "mae": 1.0324147300122868,
      "rmse": 2.1289344487090167,
      "r2": 0.2192316166897299,
      "spearman_rho": 0.6606460043440681,
      "spearman_p": 0.0,
      "haul_mae": 7.42393317809368,
      "haul_count": 1317
    },
    "baselines": {
      "zero_baseline": {
        "mae": 1.2101923076923078,
        "rmse": 2.690574716987489,
        "r2": -0.24706116051447968
      },
      "mean_baseline": {
        "mean_value": 1.2749137181405246,
        "mae": 1.5610559746682193,
        "rmse": 2.4105980172721924,
        "r2": -0.001030314899999718
      }
    },
    "improvements": {
      "vs_zero": {
        "mae_improve": 0.177777577680021,
        "rmse_improve": 0.5616402682784725,
        "r2_improve": 0.4662927772042096
      },
      "vs_mean": {
        "mae_improve": 0.5286412446559325,
        "rmse_improve": 0.28166356856317565,
        "r2_improve": 0.22026193158972962
      }
    }
  }
}