{
  "experiment": "catboost_tweedie_vp1.2",
  "horizon": 1,
  "target_col": "points_next_gw",
  "holdout_season": "2024-25",
  "train_seasons": [
    "2016-17",
    "2017-18",
    "2018-19",
    "2019-20",
    "2020-21",
    "2021-22",
    "2022-23",
    "2023-24"
  ],
  "n_train": 185149,
  "n_test": 26000,
  "n_features": 116,
  "variance_power": 1.2,
  "top_features": [
    {
      "feature": "value",
      "importance": 12.917062962640978
    },
    {
      "feature": "GW",
      "importance": 6.412481598032833
    },
    {
      "feature": "total_points_season_avg",
      "importance": 5.795094904623499
    },
    {
      "feature": "bps_season_avg",
      "importance": 4.390325745915981
    },
    {
      "feature": "minutes_lag1",
      "importance": 4.380229791238046
    },
    {
      "feature": "minutes_season_avg",
      "importance": 3.9951234810440983
    },
    {
      "feature": "games_since_start",
      "importance": 3.3147031696858784
    },
    {
      "feature": "position",
      "importance": 3.2248216812007335
    },
    {
      "feature": "minutes_trend",
      "importance": 3.2180802786186073
    },
    {
      "feature": "influence_season_avg",
      "importance": 2.9267583888635715
    },
    {
      "feature": "creativity_roll5",
      "importance": 2.9142864201191934
    },
    {
      "feature": "minutes_roll10",
      "importance": 2.5244269165963913
    },
    {
      "feature": "total_points_roll10",
      "importance": 2.4521111853255237
    },
    {
      "feature": "creativity_roll10",
      "importance": 2.1204445256916813
    },
    {
      "feature": "ict_index_roll10",
      "importance": 2.0220922150307024
    },
    {
      "feature": "played_lag1",
      "importance": 1.955328094373001
    },
    {
      "feature": "total_points_roll3",
      "importance": 1.901060621501013
    },
    {
      "feature": "minutes_roll5",
      "importance": 1.5751653288970147
    },
    {
      "feature": "ict_index_lag1",
      "importance": 1.5664737585159574
    },
    {
      "feature": "minutes_roll3",
      "importance": 1.5310131536489977
    }
  ],
  "holdout": {
    "model": {
      "mae": 1.0472201069246725,
      "rmse": 2.1198594033902523,
      "r2": 0.22587381904328663,
      "spearman_rho": 0.6599070117835857,
      "spearman_p": 0.0,
      "haul_mae": 7.3277564995977995,
      "haul_count": 1317
    },
    "baselines": {
      "zero_baseline": {
        "mae": 1.2101923076923078,
        "rmse": 2.690574716987489,
        "r2": -0.24706116051447968
      },
      "mean_baseline": {
        "mean_value": 1.2749137181405246,
        "mae": 1.5610559746682193,
        "rmse": 2.4105980172721924,
        "r2": -0.001030314899999718
      }
    },
    "improvements": {
      "vs_zero": {
        "mae_improve": 0.1629722007676353,
        "rmse_improve": 0.5707153135972369,
        "r2_improve": 0.4729349795577663
      },
      "vs_mean": {
        "mae_improve": 0.5138358677435468,
        "rmse_improve": 0.2907386138819401,
        "r2_improve": 0.22690413394328635
      }
    }
  }
}